[
  {
    "id": "1610576855731691520",
    "text": "#LoveToday #Jan4Wed collection 9,873₹, 33% occupancy (77/236), 2 shows, 2 cinemas #Chennai https://t.co/d2cAYACcUs https://t.co/S0OCK5Wc7T",
    "createdAt": "2023-01-04T10:00:20.000Z",
    "author": {
      "id": "1482202020539158529",
      "name": "tamil boxoffice",
      "username": "paytm_ta",
      "verified": false,
      "imageUrl": "https://pbs.twimg.com/profile_images/1558510080676417536/n17cJOzV_normal.jpg"
    },
    "metrics": {
      "likes": 0,
      "quotes": 0,
      "replies": 0,
      "retweets": 0
    },
    "lang": "en",
    "replySettings": "everyone",
    "media": [
      {
        "type": "photo",
        "url": "https://pbs.twimg.com/media/FlnrHJ0akAICOzo.jpg",
        "width": 608,
        "height": 800
      }
    ],
    "urls": [
      "https://github.com/HedCET/paytm-movies/blob/main/LoveToday/659e54.2023-01-04.csv",
      "https://twitter.com/paytm_ta/status/1610576855731691520/photo/1"
    ]
  }
]